LICENSE.md
README.md
pyproject.toml
khiops/__init__.py
khiops/tools.py
khiops.egg-info/PKG-INFO
khiops.egg-info/SOURCES.txt
khiops.egg-info/dependency_links.txt
khiops.egg-info/entry_points.txt
khiops.egg-info/requires.txt
khiops.egg-info/top_level.txt
khiops/core/__init__.py
khiops/core/analysis_results.py
khiops/core/api.py
khiops/core/coclustering_results.py
khiops/core/dictionary.py
khiops/core/exceptions.py
khiops/core/helpers.py
khiops/core/internals/__init__.py
khiops/core/internals/common.py
khiops/core/internals/filesystems.py
khiops/core/internals/io.py
khiops/core/internals/runner.py
khiops/core/internals/scenario.py
khiops/core/internals/task.py
khiops/core/internals/types.py
khiops/core/internals/version.py
khiops/core/internals/tasks/__init__.py
khiops/core/internals/tasks/build_deployed_dictionary.py
khiops/core/internals/tasks/build_dictionary_from_data_table.py
khiops/core/internals/tasks/check_database.py
khiops/core/internals/tasks/deploy_model.py
khiops/core/internals/tasks/detect_data_table_format.py
khiops/core/internals/tasks/detect_data_table_format_with_dictionary.py
khiops/core/internals/tasks/evaluate_predictor.py
khiops/core/internals/tasks/export_dictionary_as_json.py
khiops/core/internals/tasks/extract_clusters.py
khiops/core/internals/tasks/extract_keys_from_data_table.py
khiops/core/internals/tasks/interpret_predictor.py
khiops/core/internals/tasks/prepare_coclustering_deployment.py
khiops/core/internals/tasks/reinforce_predictor.py
khiops/core/internals/tasks/simplify_coclustering.py
khiops/core/internals/tasks/sort_data_table.py
khiops/core/internals/tasks/train_coclustering.py
khiops/core/internals/tasks/train_instance_variable_coclustering.py
khiops/core/internals/tasks/train_predictor.py
khiops/core/internals/tasks/train_recoder.py
khiops/extras/__init__.py
khiops/extras/docker.py
khiops/samples/__init__.py
khiops/samples/samples.ipynb
khiops/samples/samples.py
khiops/samples/samples_sklearn.ipynb
khiops/samples/samples_sklearn.py
khiops/sklearn/__init__.py
khiops/sklearn/dataset.py
khiops/sklearn/estimators.py
khiops/sklearn/helpers.py