Metadata-Version: 2.4
Name: khiops
Version: 11.0.0.2
Summary: Python library for the Khiops AutoML suite
Maintainer-email: The Khiops Team <khiops.team@orange.com>
License-Expression: BSD-3-Clause-Clear
Project-URL: Homepage, https://khiops.org
Classifier: Development Status :: 5 - Production/Stable
Classifier: Intended Audience :: Developers
Classifier: Intended Audience :: Science/Research
Classifier: Operating System :: MacOS
Classifier: Operating System :: Microsoft :: Windows
Classifier: Operating System :: POSIX
Classifier: Operating System :: Unix
Classifier: Programming Language :: Python
Classifier: Topic :: Scientific/Engineering
Requires-Python: >=3.8
License-File: LICENSE.md
Requires-Dist: pandas<=2.3.3,>=0.25.3
Requires-Dist: scikit-learn<=1.7.2,>=0.22.2
Provides-Extra: s3
Requires-Dist: boto3<=1.35.69,>=1.17.39; extra == "s3"
Provides-Extra: gcs
Requires-Dist: google-cloud-storage>=1.37.0; extra == "gcs"
Dynamic: license-file
